eventlogic.py
eventlogic-0.1.14.dist-info/METADATA
eventlogic-0.1.14.dist-info/WHEEL
eventlogic-0.1.14.dist-info/top_level.txt
eventlogic-0.1.14.dist-info/RECORD
