Metadata-Version: 2.1
Name: eventlogic
Version: 0.1.14
Summary: EventLogic is a lightweight library for performing logical operations on event-style or timestamp data. Logical operations on event-style data are commonplace in many fields. This library seeks to provide a generalized framework and methods for dealing with this data.
Author: Clayton Barnes
Author-email: barnes.clayton@icloud.com
License: MIT
Requires-Python: >=3.6
Requires-Dist: numpy
Requires-Dist: importlib-metadata; python_version >= "3.6"
